cellulariot/MMA8452Q.py
cellulariot/SDL_Pi_HDC1000.py
cellulariot/__init__.py
cellulariot/cellulariot.py
sixfab_cellulariot-1.2.0.dist-info/DESCRIPTION.rst
sixfab_cellulariot-1.2.0.dist-info/METADATA
sixfab_cellulariot-1.2.0.dist-info/RECORD
sixfab_cellulariot-1.2.0.dist-info/WHEEL
sixfab_cellulariot-1.2.0.dist-info/dependency_links.txt
sixfab_cellulariot-1.2.0.dist-info/metadata.json
sixfab_cellulariot-1.2.0.dist-info/top_level.txt
