Metadata-Version: 2.0
Name: sixfab-cellulariot
Version: 1.2.0
Summary: sixfab linux libraries
Home-page: https://github.com/sixfab/Sixfab_RPi_CellularIoT_App_Shield
Author: Yasin Kaya
Author-email: yasinkaya.121@gmail.com
License: MIT
Platform: UNKNOWN
Requires-Dist: Adafruit-GPIO (>=0.9.3)
Requires-Dist: adafruit-ads1x15
Requires-Dist: pyserial
